LICENSE
python_aws_ssm/__init__.py
python_aws_ssm/parameters.py
python_aws_ssm-1.0.0.dist-info/LICENSE
python_aws_ssm-1.0.0.dist-info/WHEEL
python_aws_ssm-1.0.0.dist-info/METADATA
python_aws_ssm-1.0.0.dist-info/RECORD
