Metadata-Version: 2.1
Name: python-aws-ssm
Version: 1.0.0
Summary: Python package that interfaces with AWS System Manager
Home-page: https://github.com/PaddleHQ/python-aws-ssm
License: Apache-2.0
Keywords: python,aws,ssm
Author: Luca Valentini
Author-email: luca@paddle.com
Requires-Python: >=3.7,<4.0
Classifier: License :: OSI Approved :: Apache Software License
Classifier: Programming Language :: Python :: 3
Classifier: Programming Language :: Python :: 3.7
Requires-Dist: boto3 (>=1.9,<2.0)
Project-URL: Repository, https://github.com/PaddleHQ/python-aws-ssm
